geopolrisk/__init__.py
geopolrisk/test.py
geopolrisk/assessment/__init__.py
geopolrisk/assessment/console.py
geopolrisk/assessment/core.py
geopolrisk/assessment/gprsplots.py
geopolrisk/assessment/main.py
geopolrisk/assessment/utils.py
geopolrisk/tests/__init__.py
geopolrisk/tests/defaults.py
geopolrisk/tests/test_case_1.py
geopolrisk/tests/test_case_2.py
geopolrisk/tests/test_case_3.py
geopolrisk-1.dist-info/LICENSE.txt
geopolrisk-1.dist-info/METADATA
geopolrisk-1.dist-info/WHEEL
geopolrisk-1.dist-info/top_level.txt
geopolrisk-1.dist-info/RECORD
