Metadata-Version: 2.1
Name: geopolrisk
Version: 1
Summary: A complete library for calculation of the GeoPolRisk method
Home-page: https://github.com/akoyamp/geopolrisk-py
Author: Anish Koyamparambath
Author-email: anish.koyamparambath@u-bordeaux.fr
License: GPL-3.0-or-later
Classifier: Programming Language :: Python :: 3
Classifier: License :: OSI Approved :: GNU General Public License v3 or later (GPLv3+)
Classifier: Operating System :: OS Independent
Requires-Python: >=3.7
License-File: LICENSE.txt
Requires-Dist: pandas
Requires-Dist: matplotlib
Requires-Dist: scipy
